{"blogPosts":[{"w":"0","facebookFix":"","author":"","pubDate":"10\/2\/22, 10:00 PM","tags":[],"cssClasses":["v7","ps16","s25","c35","ps18","s26","c36","p4","f7","ps24","s27","c37","f8","s28","c38","i4","i3","ps25","s29","c39","f9"],"resizeImages":"dpi=window.devicePixelRatio;var a='data-src';var e=document.querySelector('.un1');if(e.hasAttribute('src')){a='src';}e.setAttribute(a,(dpi>1)?'images\/placeholder-440.png':'images\/placeholder-220.png');","title":"Post 4","documentReady":"","documentLoad":"ldsrcset('.un6 source');","animations":"","html":"<div class=\"v7 ps16 s25 c35\">\n<div class=\"v7 ps18 s26 c36\">\n<h2 class=\"p4\"><span class=\"f7\"><a href=\"#\">Post 4<\/a><\/span><\/h2>\n<\/div>\n<div class=\"v7 ps24 s27 c37\">\n<h3 class=\"p4 f8\">03\/10\/2022<\/h3>\n<\/div>\n<div class=\"v7 ps18 s28 c38\">\n<picture class=\"i4 un6\">\n<source data-srcset=\"images\/placeholder-220.webp 1x, images\/placeholder-440.webp 2x\" srcset=\"data:image\/gif;base64,R0lGODlhAQABAIAAAAAAAP\/\/\/yH5BAEAAAAALAAAAAABAAEAAAIBRAA7\" type=\"image\/webp\">\n<source data-srcset=\"images\/placeholder-220.png 1x, images\/placeholder-440.png 2x\" srcset=\"data:image\/gif;base64,R0lGODlhAQABAIAAAAAAAP\/\/\/yH5BAEAAAAALAAAAAABAAEAAAIBRAA7\">\n<img src=\"images\/placeholder-440.png\" class=\"un1 i3\">\n<\/picture>\n<\/div>\n<div class=\"v7 ps25 s29 c39\">\n<p class=\"p4 f9\">Hello,<\/p>\n<p class=\"p4 f9\">this is a new blog post (no. 2).<\/p>\n<p class=\"p4 f9\"><br><\/p>\n<p class=\"p4 f9\"><br><\/p>\n<p class=\"p4 f9\">tralala<\/p>\n<\/div>\n<\/div>"},{"w":"0","facebookFix":"","author":"","pubDate":"10\/2\/22, 10:00 PM","tags":[],"cssClasses":["v7","ps16","s25","c40","ps18","s26","c41","p4","f7","ps24","s27","c42","f8","s28","c43","i4","i3","ps25","s29","c44","f9"],"resizeImages":"dpi=window.devicePixelRatio;var a='data-src';var e=document.querySelector('.un2');if(e.hasAttribute('src')){a='src';}e.setAttribute(a,(dpi>1)?'images\/placeholder-440.png':'images\/placeholder-220.png');","title":"Post 3","documentReady":"","documentLoad":"ldsrcset('.un7 source');","animations":"","html":"<div class=\"v7 ps16 s25 c40\">\n<div class=\"v7 ps18 s26 c41\">\n<h2 class=\"p4\"><span class=\"f7\"><a href=\"#\">Post 3<\/a><\/span><\/h2>\n<\/div>\n<div class=\"v7 ps24 s27 c42\">\n<h3 class=\"p4 f8\">03\/10\/2022<\/h3>\n<\/div>\n<div class=\"v7 ps18 s28 c43\">\n<picture class=\"i4 un7\">\n<source data-srcset=\"images\/placeholder-220.webp 1x, images\/placeholder-440.webp 2x\" srcset=\"data:image\/gif;base64,R0lGODlhAQABAIAAAAAAAP\/\/\/yH5BAEAAAAALAAAAAABAAEAAAIBRAA7\" type=\"image\/webp\">\n<source data-srcset=\"images\/placeholder-220.png 1x, images\/placeholder-440.png 2x\" srcset=\"data:image\/gif;base64,R0lGODlhAQABAIAAAAAAAP\/\/\/yH5BAEAAAAALAAAAAABAAEAAAIBRAA7\">\n<img src=\"images\/placeholder-440.png\" class=\"un2 i3\">\n<\/picture>\n<\/div>\n<div class=\"v7 ps25 s29 c44\">\n<p class=\"p4 f9\">Hello,<\/p>\n<p class=\"p4 f9\">this is a new blog post (no. 2).<\/p>\n<p class=\"p4 f9\"><br><\/p>\n<p class=\"p4 f9\"><br><\/p>\n<p class=\"p4 f9\">tralala<\/p>\n<\/div>\n<\/div>"},{"w":"0","facebookFix":"","author":"","pubDate":"10\/2\/22, 10:00 PM","tags":[],"cssClasses":["v7","ps16","s25","c45","ps18","s26","c46","p4","f7","ps24","s27","c47","f8","s28","c48","i4","i3","ps25","s29","c49","f9"],"resizeImages":"dpi=window.devicePixelRatio;var a='data-src';var e=document.querySelector('.un3');if(e.hasAttribute('src')){a='src';}e.setAttribute(a,(dpi>1)?'images\/placeholder-440.png':'images\/placeholder-220.png');","title":"Post 2","documentReady":"","documentLoad":"ldsrcset('.un8 source');","animations":"","html":"<div class=\"v7 ps16 s25 c45\">\n<div class=\"v7 ps18 s26 c46\">\n<h2 class=\"p4\"><span class=\"f7\"><a href=\"#\">Post 2<\/a><\/span><\/h2>\n<\/div>\n<div class=\"v7 ps24 s27 c47\">\n<h3 class=\"p4 f8\">03\/10\/2022<\/h3>\n<\/div>\n<div class=\"v7 ps18 s28 c48\">\n<picture class=\"i4 un8\">\n<source data-srcset=\"images\/placeholder-220.webp 1x, images\/placeholder-440.webp 2x\" srcset=\"data:image\/gif;base64,R0lGODlhAQABAIAAAAAAAP\/\/\/yH5BAEAAAAALAAAAAABAAEAAAIBRAA7\" type=\"image\/webp\">\n<source data-srcset=\"images\/placeholder-220.png 1x, images\/placeholder-440.png 2x\" srcset=\"data:image\/gif;base64,R0lGODlhAQABAIAAAAAAAP\/\/\/yH5BAEAAAAALAAAAAABAAEAAAIBRAA7\">\n<img src=\"images\/placeholder-440.png\" class=\"un3 i3\">\n<\/picture>\n<\/div>\n<div class=\"v7 ps25 s29 c49\">\n<p class=\"p4 f9\">Hello,<\/p>\n<p class=\"p4 f9\">this is a new blog post (no. 2).<\/p>\n<p class=\"p4 f9\"><br><\/p>\n<p class=\"p4 f9\"><br><\/p>\n<p class=\"p4 f9\">tralala<\/p>\n<\/div>\n<\/div>"},{"w":"0","facebookFix":"","author":"","pubDate":"10\/2\/22, 10:00 PM","tags":[],"cssClasses":["v4","ps7","s7","c8","ps8","s8","c9","p2","f2","ps9","s9","c10","f3","s10","c11","i2","i1","ps10","s11","c12","f4"],"resizeImages":"dpi=window.devicePixelRatio;var a='data-src';var e=document.querySelector('.un4');if(e.hasAttribute('src')){a='src';}e.setAttribute(a,(dpi>1)?'images\/placeholder-440.png':'images\/placeholder-220.png');","title":"Post 1","documentReady":"","documentLoad":"ldsrcset('.un5 source');","animations":"","html":"<div class=\"v4 ps7 s7 c8\">\n<div class=\"v4 ps8 s8 c9\">\n<h2 class=\"p2\"><span class=\"f2\"><a href=\"post-1.html\">Post 1<\/a><\/span><\/h2>\n<\/div>\n<div class=\"v4 ps9 s9 c10\">\n<h3 class=\"p2 f3\">03\/10\/2022<\/h3>\n<\/div>\n<div class=\"v4 ps8 s10 c11\">\n<picture class=\"i2 un5\">\n<source data-srcset=\"images\/placeholder-220.webp 1x, images\/placeholder-440.webp 2x\" srcset=\"data:image\/gif;base64,R0lGODlhAQABAIAAAAAAAP\/\/\/yH5BAEAAAAALAAAAAABAAEAAAIBRAA7\" type=\"image\/webp\">\n<source data-srcset=\"images\/placeholder-220.png 1x, images\/placeholder-440.png 2x\" srcset=\"data:image\/gif;base64,R0lGODlhAQABAIAAAAAAAP\/\/\/yH5BAEAAAAALAAAAAABAAEAAAIBRAA7\">\n<img src=\"images\/placeholder-440.png\" class=\"un4 i1\">\n<\/picture>\n<\/div>\n<div class=\"v4 ps10 s11 c12\">\n<p class=\"p2 f4\">Hello,<\/p>\n<p class=\"p2 f4\">this is a new blog post (no. 1).<\/p>\n<\/div>\n<\/div>"}],"blogPostsPerPage":4,"devices":["default:960"],"css":{"default":{"v4":".v4{display:inline-block;vertical-align:top}","c12":".c12{z-index:24;pointer-events:auto;overflow:hidden;height:229px}","c39":".c39{z-index:9;pointer-events:auto;overflow:hidden;height:229px}","ps7":".ps7{position:relative;margin-top:0}","s9":".s9{min-width:104px;width:104px;min-height:41px}","c45":".c45{z-index:16}","ps8":".ps8{position:relative;margin-left:10px;margin-top:0}","v7":".v7{display:inline-block;vertical-align:top}","c46":".c46{z-index:17;pointer-events:auto;overflow:hidden;height:47px}","p2":".p2{text-indent:0;padding-bottom:0;padding-right:0;text-align:left}","f2":".f2{font-family:Poppins;font-size:18px;font-size:calc(18px * var(--f));line-height:1.779;font-weight:400;font-style:normal;text-decoration:underline;text-transform:none;letter-spacing:normal;color:#000;background-color:initial;text-shadow:none}","s10":".s10{min-width:220px;width:220px;min-height:229px;height:229px}","ps9":".ps9{position:relative;margin-left:116px;margin-top:0}","f3":".f3{font-family:Poppins;font-size:18px;font-size:calc(18px * var(--f));line-height:1.779;font-weight:400;font-style:normal;text-decoration:none;text-transform:none;letter-spacing:normal;color:#000;background-color:initial;text-shadow:none}","c47":".c47{z-index:18;pointer-events:auto;overflow:hidden;height:41px}","p4":".p4{text-indent:0;padding-bottom:0;padding-right:0;text-align:left}","ps16":".ps16{position:relative;margin-top:0}","c8":".c8{z-index:21}","s11":".s11{min-width:700px;width:700px;min-height:229px}","ps24":".ps24{position:relative;margin-left:116px;margin-top:0}","c9":".c9{z-index:22;pointer-events:auto;overflow:hidden;height:47px}","c40":".c40{z-index:11}","s25":".s25{width:100%;min-width:960px;min-height:276px}","c48":".c48{z-index:20;pointer-events:auto}","i1":".i1{position:absolute;left:0;width:220px;height:229px;top:0}","c35":".c35{z-index:6}","f4":".f4{font-family:Poppins;font-size:18px;font-size:calc(18px * var(--f));line-height:2.279;font-weight:400;font-style:normal;text-decoration:none;text-transform:none;letter-spacing:normal;color:#000;background-color:initial;text-shadow:none}","i2":".i2{width:100%;height:100%;display:inline-block;-webkit-transform:translate3d(0,0,0)}","c41":".c41{z-index:12;pointer-events:auto;overflow:hidden;height:47px}","f7":".f7{font-family:Poppins;font-size:18px;font-size:calc(18px * var(--f));line-height:1.779;font-weight:400;font-style:normal;text-decoration:underline;text-transform:none;letter-spacing:normal;color:#000;background-color:initial;text-shadow:none}","c49":".c49{z-index:19;pointer-events:auto;overflow:hidden;height:229px}","i3":".i3{position:absolute;left:0;width:220px;height:229px;top:0}","c36":".c36{z-index:7;pointer-events:auto;overflow:hidden;height:47px}","s26":".s26{min-width:720px;width:720px;min-height:47px}","f8":".f8{font-family:Poppins;font-size:18px;font-size:calc(18px * var(--f));line-height:1.779;font-weight:400;font-style:normal;text-decoration:none;text-transform:none;letter-spacing:normal;color:#000;background-color:initial;text-shadow:none}","ps25":".ps25{position:relative;margin-left:20px;margin-top:0}","i4":".i4{width:100%;height:100%;display:inline-block;-webkit-transform:translate3d(0,0,0)}","c42":".c42{z-index:13;pointer-events:auto;overflow:hidden;height:41px}","s27":".s27{min-width:104px;width:104px;min-height:41px}","f9":".f9{font-family:Poppins;font-size:18px;font-size:calc(18px * var(--f));line-height:2.279;font-weight:400;font-style:normal;text-decoration:none;text-transform:none;letter-spacing:normal;color:#000;background-color:initial;text-shadow:none}","c10":".c10{z-index:23;pointer-events:auto;overflow:hidden;height:41px}","c37":".c37{z-index:8;pointer-events:auto;overflow:hidden;height:41px}","c43":".c43{z-index:15;pointer-events:auto}","s28":".s28{min-width:220px;width:220px;min-height:229px;height:229px}","ps18":".ps18{position:relative;margin-left:10px;margin-top:0}","s7":".s7{width:100%;min-width:960px;min-height:276px}","c38":".c38{z-index:10;pointer-events:auto}","c11":".c11{z-index:25;pointer-events:auto}","ps10":".ps10{position:relative;margin-left:20px;margin-top:0}","s8":".s8{min-width:720px;width:720px;min-height:47px}","c44":".c44{z-index:14;pointer-events:auto;overflow:hidden;height:229px}","s29":".s29{min-width:700px;width:700px;min-height:229px}"}},"mq":{},"blogPostsMargin":{"default":10}}